{
  "trained_at": "2025-12-07T03:40:01.562968",
  "watchlist_size": 56,
  "successful_tickers": [
    "SERV",
    "APLD",
    "HOOD",
    "MVST",
    "RR",
    "LUNR",
    "IONQ",
    "AVGO",
    "QCOM",
    "SQFT",
    "UUUU",
    "UPC",
    "DGNX",
    "TSLA",
    "ALB",
    "DLB",
    "PALI",
    "ELWS",
    "MU",
    "NEM",
    "SMR",
    "LEU",
    "XME",
    "KRYS",
    "UNH",
    "WMT",
    "PG",
    "AQMS",
    "OKLO",
    "RXRX",
    "TEVA",
    "MTZ",
    "LLY",
    "QTUM",
    "TOL",
    "GME",
    "SOFI",
    "COST",
    "AVAV",
    "CEG",
    "GEO",
    "MRVL",
    "AAPL",
    "NVDA",
    "AMZN",
    "SNOW",
    "WDC",
    "BSX",
    "CXW",
    "PCAR",
    "UBER",
    "LYFT",
    "MNDY",
    "BA"
  ],
  "total_samples": 23524,
  "train_samples": 18819,
  "test_samples": 4705,
  "features": 7,
  "models": {
    "lightgbm": {
      "train": 0.7912216377065732,
      "test": 0.7455897980871413
    },
    "xgboost": {
      "train": 0.8028588129018545,
      "test": 0.7379383634431456
    },
    "histgb": {
      "train": 0.7944099048833626,
      "test": 0.7432518597236982
    }
  },
  "best_model": "lightgbm",
  "best_accuracy": 0.7455897980871413
}